flotorch_eval/__init__.py
flotorch_eval/agent_eval/__init__.py
flotorch_eval/agent_eval/core/__init__.py
flotorch_eval/agent_eval/core/client.py
flotorch_eval/agent_eval/core/converter.py
flotorch_eval/agent_eval/core/schemas.py
flotorch_eval/agent_eval/metrics/__init__.py
flotorch_eval/agent_eval/metrics/base.py
flotorch_eval/agent_eval/metrics/latency_metrics.py
flotorch_eval/agent_eval/metrics/llm_evaluators.py
flotorch_eval/agent_eval/metrics/prompt_manager.py
flotorch_eval/agent_eval/metrics/usage_metrics.py
flotorch_eval/agent_eval/metrics/prompts/agent_goal_accuracy.txt
flotorch_eval/agent_eval/metrics/prompts/toolcall_accuracy.txt
flotorch_eval/agent_eval/metrics/prompts/trajectory_evaluation.txt
flotorch_eval/agent_eval/metrics/prompts/trajectory_evaluation_with_reference.txt
flotorch_eval/common/__init__.py
flotorch_eval/common/cost_compute_utils.py
flotorch_eval/common/cost_utils.py
flotorch_eval/common/display_utils.py
flotorch_eval/common/latency_utils.py
flotorch_eval/common/metrics.py
flotorch_eval/common/token_utils.py
flotorch_eval/llm_eval/__init__.py
flotorch_eval/llm_eval/core/__init__.py
flotorch_eval/llm_eval/core/base_evaluator.py
flotorch_eval/llm_eval/core/client.py
flotorch_eval/llm_eval/core/deepeval_evaluator.py
flotorch_eval/llm_eval/core/gateway_evaluator.py
flotorch_eval/llm_eval/core/ragas_evaluator.py
flotorch_eval/llm_eval/core/schemas.py
flotorch_eval/llm_eval/metrics/__init__.py
flotorch_eval/llm_eval/metrics/base_metrics.py
flotorch_eval/llm_eval/metrics/metric_keys.py
flotorch_eval/llm_eval/metrics/deepeval_metrics/deepeval_metrics.py
flotorch_eval/llm_eval/metrics/gateway_metrics/__init__.py
flotorch_eval/llm_eval/metrics/gateway_metrics/gateway_metrics.py
flotorch_eval/llm_eval/metrics/ragas_metrics/base_metric.py
flotorch_eval/llm_eval/metrics/ragas_metrics/metric_keys.py
flotorch_eval/llm_eval/metrics/ragas_metrics/ragas_metrics.py
flotorch_eval-2.0.0.dist-info/METADATA
flotorch_eval-2.0.0.dist-info/WHEEL
flotorch_eval-2.0.0.dist-info/licenses/LICENSE
flotorch_eval-2.0.0.dist-info/RECORD
