Metadata-Version: 2.4
Name: flotorch-eval
Version: 2.0.0
Summary: A comprehensive evaluation framework for AI systems
Project-URL: Homepage, https://github.com/FloTorch/flotorch-eval
Project-URL: Repository, https://github.com/FloTorch/flotorch-eval
Project-URL: Issues, https://github.com/FloTorch/flotorch-eval/issues
Author-email: Nanda Rajashekaruni <nanda@flotorch.ai>, Kiran George <kiran.george@flotorch.ai>
License: MIT
License-File: LICENSE
Keywords: agents,ai,evaluation,models,opentelemetry,ragas
Classifier: Development Status :: 3 - Alpha
Classifier: Intended Audience :: Developers
Classifier: License :: OSI Approved :: MIT License
Classifier: Programming Language :: Python :: 3
Classifier: Programming Language :: Python :: 3.8
Classifier: Programming Language :: Python :: 3.9
Classifier: Programming Language :: Python :: 3.10
Classifier: Programming Language :: Python :: 3.11
Requires-Python: >=3.8
Requires-Dist: deepeval==3.6.9
Requires-Dist: flotorch>=2.0.0
Requires-Dist: opentelemetry-api>=1.0.0
Requires-Dist: opentelemetry-sdk>=1.0.0
Requires-Dist: pydantic>=2.0.0
Requires-Dist: ragas==0.3.8
Requires-Dist: requests>=2.28.0
Requires-Dist: typing-extensions>=4.7.0
Provides-Extra: dev
Requires-Dist: black>=22.0.0; extra == 'dev'
Requires-Dist: flake8>=4.0.0; extra == 'dev'
Requires-Dist: isort>=5.0.0; extra == 'dev'
Requires-Dist: mypy>=1.0.0; extra == 'dev'
Requires-Dist: pytest-asyncio>=0.14.0; extra == 'dev'
Requires-Dist: pytest-cov>=2.0.0; extra == 'dev'
Requires-Dist: pytest>=7.0.0; extra == 'dev'
